x2embedding/__init__.py
x2embedding/zoo.py
x2embedding/clis/README.md
x2embedding/clis/__init__.py
x2embedding/clis/cli.py
x2embedding-2022.3.16.9.34.14.dist-info/AUTHORS.rst
x2embedding-2022.3.16.9.34.14.dist-info/LICENSE
x2embedding-2022.3.16.9.34.14.dist-info/METADATA
x2embedding-2022.3.16.9.34.14.dist-info/WHEEL
x2embedding-2022.3.16.9.34.14.dist-info/entry_points.txt
x2embedding-2022.3.16.9.34.14.dist-info/top_level.txt
x2embedding-2022.3.16.9.34.14.dist-info/RECORD
