Metadata-Version: 2.1
Name: x2embedding
Version: 2022.3.16.9.34.14
Summary: Create a Python package.
Home-page: https://github.com/Jie-Yuan/x2embedding
Author: x2embedding
Author-email: yuanjie@example.com
License: MIT license
Keywords: x2embedding
Platform: UNKNOWN
Classifier: Development Status :: 2 - Pre-Alpha
Classifier: Intended Audience :: Developers
Classifier: License :: OSI Approved :: MIT License
Classifier: Natural Language :: English
Classifier: Programming Language :: Python :: 3
Classifier: Programming Language :: Python :: 3.6
Classifier: Programming Language :: Python :: 3.7
Classifier: Programming Language :: Python :: 3.8
Requires-Python: >=3.6
License-File: LICENSE
License-File: AUTHORS.rst
Requires-Dist: meutils
